ovos_bm25_solver/__init__.py
ovos_bm25_solver/base.py
ovos_bm25_solver/corpus.py
ovos_bm25_solver/demo.py
ovos_bm25_solver/embed.py
ovos_bm25_solver/version.py
ovos_solver_bm25_plugin-0.0.1.dist-info/METADATA
ovos_solver_bm25_plugin-0.0.1.dist-info/WHEEL
ovos_solver_bm25_plugin-0.0.1.dist-info/entry_points.txt
ovos_solver_bm25_plugin-0.0.1.dist-info/top_level.txt
ovos_solver_bm25_plugin-0.0.1.dist-info/zip-safe
ovos_solver_bm25_plugin-0.0.1.dist-info/RECORD
