Metadata-Version: 2.1
Name: ovos-solver-bm25-plugin
Version: 0.0.1
Summary: A question solver plugin for OVOS
Home-page: https://github.com/TigreGotico/ovos-solver-BM25-plugin
Author: jarbasai
Author-email: jarbasai@mailfence.com
License: MIT
Keywords: OVOS openvoiceos plugin utterance fallback query
Requires-Dist: ovos-plugin-manager>=0.8.5
Requires-Dist: bm25s
Requires-Dist: quebra-frases
Requires-Dist: rapidfuzz
Requires-Dist: json-database
